telegram/__init__.py
telegram/exception.py
telegram/helpers.py
telegram/py.typed
telegram/sdk.py
telegram_sdk-1.2.2.dist-info/licenses/LICENSE
telegram_sdk-1.2.2.dist-info/METADATA
telegram_sdk-1.2.2.dist-info/WHEEL
telegram_sdk-1.2.2.dist-info/top_level.txt
telegram_sdk-1.2.2.dist-info/RECORD
