Metadata-Version: 2.4
Name: telegram-sdk
Version: 1.2.2
Summary: Telegram SDK for public or private Telegram API
Author-email: "Golden M, Inc." <software@goldenm.com>
Maintainer-email: Kenny Mochizuki <kenny@goldenm.com>
License: MIT License
Keywords: telegram,api,bot,sdk,layrz,goldenm
Classifier: Programming Language :: Python :: 3
Classifier: Programming Language :: Python :: 3.10
Classifier: Programming Language :: Python :: 3.11
Classifier: Programming Language :: Python :: 3.12
Requires-Python: >=3.10
License-File: LICENSE
Requires-Dist: requests>=2.32.3
Requires-Dist: tzdata>=2025.2
Dynamic: license-file
